.coveragerc
.flake8
AUTHORS
ChangeLog
Dockerfile
LICENSE
MANIFEST.in
README.md
codecov.yml
nose.cfg
requirements-dev.txt
requirements-test.txt
requirements.txt
setup.cfg
setup.py
tox.ini
.circleci/config.yml
bin/analyze
bin/coverage
bin/deploy
bin/install
bin/lint
bin/readme
bin/tag
bin/test
kms_vault/__init__.py
kms_vault/utils.py
kms_vault/vault.py
kms_vault.egg-info/PKG-INFO
kms_vault.egg-info/SOURCES.txt
kms_vault.egg-info/dependency_links.txt
kms_vault.egg-info/entry_points.txt
kms_vault.egg-info/not-zip-safe
kms_vault.egg-info/pbr.json
kms_vault.egg-info/requires.txt
kms_vault.egg-info/top_level.txt
kms_vault/scripts/__init__.py
kms_vault/scripts/kms_vault.py
tests/__init__.py
tests/test_scripts.py
tests/test_utils.py
tests/test_vault.py
tests/utils.py
tests/fixtures/secrets.yml