Metadata-Version: 2.1
Name: kms-vault
Version: 0.3.0
Summary: A simple pip installable library for encrypting secrets using the AWS key management service.
Home-page: https://github.com/hangarunderground/kms-vault
Author: Anthony Almarza
Author-email: anthony.almarza@gmail.com
License: MIT
Keywords: aws,kms,vault,secrets,encryption,security
Platform: UNKNOWN
Classifier: Development Status :: 4 - Beta
Classifier: Environment :: Console
Classifier: Intended Audience :: Developers
Classifier: Intended Audience :: Information Technology
Classifier: License :: OSI Approved :: MIT License
Classifier: Operating System :: OS Independent
Classifier: Programming Language :: Python
